starfieldsaver/__init__.py
starfieldsaver/config_loader.py
starfieldsaver/main.py
starfieldsaver/process_monitor.py
starfieldsaver/quicksaver.py
starfieldsaver/save_cleaner.py
starfieldsaver/sound_player.py
starfieldsaver/tools/__init__.py
starfieldsaver/tools/renumber_saves.py
starfieldsaver/types.py
starfieldsaver-0.2.6.dist-info/LICENSE
starfieldsaver-0.2.6.dist-info/METADATA
starfieldsaver-0.2.6.dist-info/WHEEL
starfieldsaver-0.2.6.dist-info/entry_points.txt
starfieldsaver-0.2.6.dist-info/RECORD
