Metadata-Version: 2.3
Name: starfieldsaver
Version: 0.2.6
Summary: Starfield automatic quicksave and backup utility
License: MIT
Author: Danny Stewart
Author-email: danny@stewart.cc
Requires-Python: >=3.12,<3.14
Classifier: Development Status :: 4 - Beta
Classifier: Environment :: Console
Classifier: Intended Audience :: End Users/Desktop
Classifier: License :: OSI Approved :: MIT License
Classifier: Natural Language :: English
Classifier: Operating System :: Microsoft :: Windows
Classifier: Programming Language :: Python :: 3
Classifier: Programming Language :: Python :: 3.12
Classifier: Programming Language :: Python :: 3.13
Classifier: Topic :: Games/Entertainment
Classifier: Topic :: Games/Entertainment :: Role-Playing
Requires-Dist: natsort (>=8.4.0,<9.0.0)
Requires-Dist: numpy (>=2.2.6,<3.0.0)
Requires-Dist: polykit (>=0.11.1)
Requires-Dist: psutil (>=7.0.0,<8.0.0)
Requires-Dist: pygame (>=2.6.1,<3.0.0)
Requires-Dist: pynput (>=1.8.1,<2.0.0)
Requires-Dist: pywin32 (>=310,<311) ; sys_platform == "win32"
Requires-Dist: toml (>=0.10.2,<0.11.0)
Requires-Dist: tzdata (>=2025.2,<2026.0)
Requires-Dist: watchdog (>=6.0.0,<7.0.0)
